README.md
setup.py
slackbot_wems/__init__.py
slackbot_wems/bot_id.py
slackbot_wems/slackpi.py
slackbot_wems/testit.py
slackbot_wems.egg-info/PKG-INFO
slackbot_wems.egg-info/SOURCES.txt
slackbot_wems.egg-info/dependency_links.txt
slackbot_wems.egg-info/top_level.txt
slackbot_wems/chris/__init__.py
slackbot_wems/chris/light.py
slackbot_wems/chris/segment7.py
slackbot_wems/chris/slacklib.py
slackbot_wems/joe/__init__.py
slackbot_wems/joe/led.py
slackbot_wems/joe/slacklib.py
slackbot_wems/joe/temp_humidity.py
slackbot_wems/matthew/__init__.py
slackbot_wems/matthew/slacklib.py
slackbot_wems/wems/__init__.py
slackbot_wems/wems/caroline/__init__.py
slackbot_wems/wems/caroline/slacklib.py
slackbot_wems/wems/hank/__init__.py
slackbot_wems/wems/hank/slacklib.py
slackbot_wems/wems/ibby/__init__.py
slackbot_wems/wems/ibby/slacklib.py
slackbot_wems/wems/james/__init__.py
slackbot_wems/wems/james/slacklib.py
slackbot_wems/wems/layla/__init__.py
slackbot_wems/wems/layla/slacklib.py
slackbot_wems/wems/rhyder/__init__.py
slackbot_wems/wems/rhyder/slacklib.py
slackbot_wems/wray/__init__.py
slackbot_wems/wray/slacklib.py
slackbot_wems/wray/temp_humidity.py