Metadata-Version: 1.1
Name: slackbot-wems
Version: 0.2.559936766
Summary: Python Code for Tech Em Studios WEMS Class
Home-page: https://github.com/wray/wems
Author: Techem Studios
Author-email: wray@techemstudios.com
License: UNKNOWN
Download-URL: https://github.com/wray/wems/tarball/0.2.559936766
Keywords: slackbot,RPi,AWS
Platform: UNKNOWN
